MANIFEST.in
setup.py
src/mantium.wsgi
src/mantium/__init__.py
src/mantium/main.py
src/mantium/run.py
src/mantium.egg-info/PKG-INFO
src/mantium.egg-info/SOURCES.txt
src/mantium.egg-info/dependency_links.txt
src/mantium.egg-info/entry_points.txt
src/mantium.egg-info/not-zip-safe
src/mantium.egg-info/requires.txt
src/mantium.egg-info/top_level.txt
src/mantium/models/__init__.py
src/mantium/models/base.py
src/mantium/models/build.py
src/mantium/models/log.py
src/mantium/models/project.py
src/mantium/projects/readme.md
src/mantium/static/css/layout.css
src/mantium/static/images/favicon.ico
src/mantium/static/js/main.js
src/mantium/templates/about.html.tpl
src/mantium/templates/build_files.html.tpl
src/mantium/templates/build_list.html.tpl
src/mantium/templates/build_log.html.tpl
src/mantium/templates/build_show.html.tpl
src/mantium/templates/index.html.tpl
src/mantium/templates/login.html.tpl
src/mantium/templates/project_edit.html.tpl
src/mantium/templates/project_list.html.tpl
src/mantium/templates/project_new.html.tpl
src/mantium/templates/project_show.html.tpl
src/mantium/templates/partials/content_type.html.tpl
src/mantium/templates/partials/doctype.html.tpl
src/mantium/templates/partials/end_doctype.html.tpl
src/mantium/templates/partials/footer.html.tpl
src/mantium/templates/partials/includes.html.tpl
src/mantium/templates/partials/layout.html.tpl
src/mantium/templates/partials/layout_build.html.tpl
src/mantium/templates/partials/layout_build_w.html.tpl
src/mantium/templates/partials/layout_project.html.tpl
src/mantium/templates/partials/layout_wide.html.tpl
src/mantium/views/__init__.py
src/mantium/views/web/__init__.py
src/mantium/views/web/base.py
src/mantium/views/web/build.py
src/mantium/views/web/project.py